[{"team": {"team_name": "Bayern Munich", "team_id": "27", "team_country": "Germany"}, "in": [{"player_name": "Alphonso Davies", "player_id": "424204", "player_age": "18", "player_nat": ["Canada", "Liberia"], "player_pos": "LB", "market_val": "€70.00m", "counter_team_country": "United States", "counter_team_name": "Vancouver Whitecaps FC", "counter_team_id": "6321", "transfer_fee": "€10.00m", "transfer_id": "2195457"}], "left": [{"player_name": "Sandro Wagner", "player_id": "39743", "player_age": "31", "player_nat": ["Germany"], "player_pos": "CF", "market_val": "-", "counter_team_country": "China", "counter_team_name": "Tianjin Teda", "counter_team_id": "3187", "transfer_fee": "€5.00m", "transfer_id": "2386279"}]}, {"team": {"team_name": "FC Schalke 04", "team_id": "33", "team_country": "Germany"}, "in": [{"player_name": "Rabbi Matondo", "player_id": "404384", "player_age": "18", "player_nat": ["Wales", "England"], "player_pos": "RW", "market_val": "€3.00m", "counter_team_country": "England", "counter_team_name": "Manchester City U23", "counter_team_id": "9265", "transfer_fee": "€9.00m", "transfer_id": "2387520"}, {"player_name": "Jeffrey Bruma", "player_id": "88721", "player_age": "27", "player_nat": ["Netherlands", "Suriname"], "player_pos": "CB", "market_val": "€1.00m", "counter_team_country": "Germany", "counter_team_name": "VfL Wolfsburg", "counter_team_id": "82", "transfer_fee": "loan transfer", "transfer_id": "2388764"}, {"player_name": "Ahmed Kutucu", "player_id": "452084", "player_age": "18", "player_nat": ["Turkey", "Germany"], "player_pos": "CF", "market_val": "€1.40m", "counter_team_country": "Germany", "counter_team_name": "FC Schalke 04 U19", "counter_team_id": "1463", "transfer_fee": "-", "transfer_id": "2391433"}, {"player_name": "Nassim Boujellab", "player_id": "346332", "player_age": "19", "player_nat": ["Morocco", "Germany"], "player_pos": "CM", "market_val": "€800Th.", "counter_team_country": "Germany", "counter_team_name": "FC Schalke 04 II", "counter_team_id": "34", "transfer_fee": "-", "transfer_id": "2445795"}], "left": [{"player_name": "Naldo", "player_id": "32213", "player_age": "36", "player_nat": ["Brazil", "Germany"], "player_pos": "CB", "market_val": "-", "counter_team_country": "France", "counter_team_name": "AS Monaco", "counter_team_id": "162", "transfer_fee": "€2.00m", "transfer_id": "2356427"}, {"player_name": "Johannes Geis", "player_id": "89650", "player_age": "25", "player_nat": ["Germany"], "player_pos": "DM", "market_val": "€1.60m", "counter_team_country": "Germany", "counter_team_name": "1. FC Köln", "counter_team_id": "3", "transfer_fee": "€500Th.", "transfer_id": "2367808"}, {"player_name": "Franco Di Santo", "player_id": "59783", "player_age": "29", "player_nat": ["Argentina", "Italy"], "player_pos": "CF", "market_val": "€1.00m", "counter_team_country": "Spain", "counter_team_name": "Rayo Vallecano", "counter_team_id": "367", "transfer_fee": "free transfer", "transfer_id": "2390639"}, {"player_name": "Abdul-Rahman Baba", "player_id": "224884", "player_age": "24", "player_nat": ["Ghana"], "player_pos": "LB", "market_val": "€2.50m", "counter_team_country": "England", "counter_team_name": "Chelsea FC", "counter_team_id": "631", "transfer_fee": "End of loanJan 28, 2019", "transfer_id": "2019162"}]}, {"team": {"team_name": "TSG 1899 Hoffenheim", "team_id": "533", "team_country": "Germany"}, "in": [{"player_name": "Lucas Ribeiro", "player_id": "605893", "player_age": "20", "player_nat": ["Brazil"], "player_pos": "CB", "market_val": "€2.00m", "counter_team_country": "Brazil", "counter_team_name": "Esporte Clube Vitória", "counter_team_id": "2125", "transfer_fee": "€3.00m", "transfer_id": "2384821"}, {"player_name": "Christoph Baumgartner", "player_id": "324278", "player_age": "19", "player_nat": ["Austria"], "player_pos": "AM", "market_val": "€22.00m", "counter_team_country": "Germany", "counter_team_name": "TSG 1899 Hoffenheim II", "counter_team_id": "983", "transfer_fee": "-", "transfer_id": "2369855"}], "left": [{"player_name": "Havard Nordtveit", "player_id": "42234", "player_age": "28", "player_nat": ["Norway"], "player_pos": "CB", "market_val": "€1.50m", "counter_team_country": "England", "counter_team_name": "Fulham FC", "counter_team_id": "931", "transfer_fee": "Loan fee:€1.00m", "transfer_id": "2390366"}, {"player_name": "Vincenzo Grifo", "player_id": "185077", "player_age": "25", "player_nat": ["Italy", "Germany"], "player_pos": "LW", "market_val": "€12.00m", "counter_team_country": "Germany", "counter_team_name": "SC Freiburg", "counter_team_id": "60", "transfer_fee": "Loan fee:€600Th.", "transfer_id": "2358749"}, {"player_name": "Steven Zuber", "player_id": "68033", "player_age": "27", "player_nat": ["Switzerland"], "player_pos": "LM", "market_val": "€3.50m", "counter_team_country": "Germany", "counter_team_name": "VfB Stuttgart", "counter_team_id": "79", "transfer_fee": "Loan fee:€600Th.", "transfer_id": "2361882"}, {"player_name": "Felipe Pires", "player_id": "327911", "player_age": "23", "player_nat": ["Brazil"], "player_pos": "RW", "market_val": "€800Th.", "counter_team_country": "Brazil", "counter_team_name": "Sociedade Esportiva Palmeiras", "counter_team_id": "1023", "transfer_fee": "Loan fee:€400Th.", "transfer_id": "2345395"}, {"player_name": "Kevin Akpoguma", "player_id": "160241", "player_age": "23", "player_nat": ["Nigeria", "Germany"], "player_pos": "CB", "market_val": "€5.00m", "counter_team_country": "Germany", "counter_team_name": "Hannover 96", "counter_team_id": "42", "transfer_fee": "Loan fee:€220Th.", "transfer_id": "2350974"}, {"player_name": "Gregor Kobel", "player_id": "257814", "player_age": "21", "player_nat": ["Switzerland"], "player_pos": "GK", "market_val": "€18.00m", "counter_team_country": "Germany", "counter_team_name": "FC Augsburg", "counter_team_id": "167", "transfer_fee": "Loan fee:€150Th.", "transfer_id": "2356242"}, {"player_name": "Justin Hoogma", "player_id": "411287", "player_age": "20", "player_nat": ["Netherlands"], "player_pos": "CB", "market_val": "€2.00m", "counter_team_country": "Germany", "counter_team_name": "FC St. Pauli", "counter_team_id": "35", "transfer_fee": "Loan fee:€50Th.", "transfer_id": "2387474"}]}, {"team": {"team_name": "Borussia Dortmund", "team_id": "16", "team_country": "Germany"}, "in": [{"player_name": "Leonardo Balerdi", "player_id": "575998", "player_age": "19", "player_nat": ["Argentina", "Italy"], "player_pos": "CB", "market_val": "€10.00m", "counter_team_country": "Argentina", "counter_team_name": "Club Atlético Boca Juniors", "counter_team_id": "189", "transfer_fee": "€15.50m", "transfer_id": "2368414"}, {"player_name": "Christian Pulisic", "player_id": "315779", "player_age": "20", "player_nat": ["United States", "Croatia"], "player_pos": "RW", "market_val": "€50.00m", "counter_team_country": "England", "counter_team_name": "Chelsea FC", "counter_team_id": "631", "transfer_fee": "loan transfer", "transfer_id": "2354713"}], "left": [{"player_name": "Christian Pulisic", "player_id": "315779", "player_age": "20", "player_nat": ["United States", "Croatia"], "player_pos": "RW", "market_val": "€50.00m", "counter_team_country": "England", "counter_team_name": "Chelsea FC", "counter_team_id": "631", "transfer_fee": "€64.00m", "transfer_id": "2354712"}, {"player_name": "Dzenis Burnic", "player_id": "251295", "player_age": "20", "player_nat": ["Germany", "Bosnia-Herzegovina"], "player_pos": "DM", "market_val": "€800Th.", "counter_team_country": "Germany", "counter_team_name": "SG Dynamo Dresden", "counter_team_id": "129", "transfer_fee": "Loan fee:€300Th.", "transfer_id": "2388685"}, {"player_name": "Shinji Kagawa", "player_id": "81785", "player_age": "29", "player_nat": ["Japan"], "player_pos": "AM", "market_val": "€1.20m", "counter_team_country": "Turkey", "counter_team_name": "Besiktas JK", "counter_team_id": "114", "transfer_fee": "loan transfer", "transfer_id": "2390045"}, {"player_name": "Sebastian Rode", "player_id": "44466", "player_age": "28", "player_nat": ["Germany"], "player_pos": "CM", "market_val": "€4.00m", "counter_team_country": "Germany", "counter_team_name": "Eintracht Frankfurt", "counter_team_id": "24", "transfer_fee": "loan transfer", "transfer_id": "2348897"}, {"player_name": "Alexander Isak", "player_id": "349066", "player_age": "19", "player_nat": ["Sweden", "Eritrea"], "player_pos": "CF", "market_val": "€40.00m", "counter_team_country": "Netherlands", "counter_team_name": "Willem II Tilburg", "counter_team_id": "403", "transfer_fee": "loan transfer", "transfer_id": "2381677"}, {"player_name": "Jeremy Toljan", "player_id": "129674", "player_age": "24", "player_nat": ["Germany", "United States"], "player_pos": "RB", "market_val": "€5.00m", "counter_team_country": "Scotland", "counter_team_name": "Celtic FC", "counter_team_id": "371", "transfer_fee": "loan transfer", "transfer_id": "2390494"}]}, {"team": {"team_name": "Bayer 04 Leverkusen", "team_id": "15", "team_country": "Germany"}, "in": [{"player_name": "Jan Boller", "player_id": "389079", "player_age": "18", "player_nat": ["Germany"], "player_pos": "CB", "market_val": "€500Th.", "counter_team_country": "Germany", "counter_team_name": "Bayer 04 Leverkusen U19", "counter_team_id": "4713", "transfer_fee": "-", "transfer_id": "2402405"}], "left": [{"player_name": "Jakub Bednarczyk", "player_id": "346328", "player_age": "20", "player_nat": ["Poland", "Germany"], "player_pos": "RB", "market_val": "€200Th.", "counter_team_country": "Germany", "counter_team_name": "FC St. Pauli", "counter_team_id": "35", "transfer_fee": "free transfer", "transfer_id": "2377685"}, {"player_name": "Tomasz Kucz", "player_id": "320954", "player_age": "19", "player_nat": ["Poland"], "player_pos": "GK", "market_val": "€250Th.", "counter_team_country": "Slovakia", "counter_team_name": "DAC Dunajska Streda", "counter_team_id": "4529", "transfer_fee": "loan transfer", "transfer_id": "2379079"}]}, {"team": {"team_name": "RB Leipzig", "team_id": "23826", "team_country": "Germany"}, "in": [{"player_name": "Amadou Haidara", "player_id": "402008", "player_age": "20", "player_nat": ["Mali"], "player_pos": "CM", "market_val": "€24.00m", "counter_team_country": "Austria", "counter_team_name": "Red Bull Salzburg", "counter_team_id": "409", "transfer_fee": "€19.00m", "transfer_id": "2345667"}, {"player_name": "Tyler Adams", "player_id": "332705", "player_age": "19", "player_nat": ["United States"], "player_pos": "DM", "market_val": "€20.00m", "counter_team_country": "United States", "counter_team_name": "New York Red Bulls", "counter_team_id": "623", "transfer_fee": "€2.63m", "transfer_id": "2328148"}, {"player_name": "Emile Smith Rowe", "player_id": "392765", "player_age": "18", "player_nat": ["England"], "player_pos": "AM", "market_val": "€28.00m", "counter_team_country": "England", "counter_team_name": "Arsenal FC U23", "counter_team_id": "9249", "transfer_fee": "Loan fee:€1.00m", "transfer_id": "2389345"}, {"player_name": "Felix Beiersdorf", "player_id": "248764", "player_age": "20", "player_nat": ["Germany"], "player_pos": "CM", "market_val": "-", "counter_team_country": "Germany", "counter_team_name": "ZFC Meuselwitz", "counter_team_id": "2643", "transfer_fee": "End of loanDec 31, 2018", "transfer_id": "2172997"}], "left": [{"player_name": "Felix Beiersdorf", "player_id": "248764", "player_age": "20", "player_nat": ["Germany"], "player_pos": "CM", "market_val": "-", "counter_team_country": "Germany", "counter_team_name": "Leipziger SV Südwest", "counter_team_id": "41855", "transfer_fee": "free transfer", "transfer_id": "2361603"}, {"player_name": "Emre Aslan", "player_id": "393203", "player_age": "19", "player_nat": ["Turkey", "Germany"], "player_pos": "LW", "market_val": "€50Th.", "counter_team_country": "Germany", "counter_team_name": "1.FC Nuremberg II", "counter_team_id": "473", "transfer_fee": "free transfer", "transfer_id": "2397949"}]}, {"team": {"team_name": "VfB Stuttgart", "team_id": "79", "team_country": "Germany"}, "in": [{"player_name": "Ozan Kabak", "player_id": "361260", "player_age": "18", "player_nat": ["Turkey"], "player_pos": "CB", "market_val": "€17.00m", "counter_team_country": "Turkey", "counter_team_name": "Galatasaray A.S.", "counter_team_id": "141", "transfer_fee": "€11.00m", "transfer_id": "2372450"}, {"player_name": "Steven Zuber", "player_id": "68033", "player_age": "27", "player_nat": ["Switzerland"], "player_pos": "LM", "market_val": "€3.50m", "counter_team_country": "Germany", "counter_team_name": "TSG 1899 Hoffenheim", "counter_team_id": "533", "transfer_fee": "Loan fee:€600Th.", "transfer_id": "2361882"}, {"player_name": "Alexander Esswein", "player_id": "45662", "player_age": "28", "player_nat": ["Germany"], "player_pos": "RW", "market_val": "€500Th.", "counter_team_country": "Germany", "counter_team_name": "Hertha BSC", "counter_team_id": "44", "transfer_fee": "Loan fee:€400Th.", "transfer_id": "2345706"}], "left": [{"player_name": "Nunoo Sarpei", "player_id": "451340", "player_age": "20", "player_nat": ["Ghana"], "player_pos": "DM", "market_val": "€700Th.", "counter_team_country": "Germany", "counter_team_name": "SpVgg Greuther Fürth", "counter_team_id": "65", "transfer_fee": "Loan fee:€50Th.", "transfer_id": "2380047"}, {"player_name": "Berkay Özcan", "player_id": "249952", "player_age": "20", "player_nat": ["Turkey", "Germany"], "player_pos": "CM", "market_val": "€3.00m", "counter_team_country": "Germany", "counter_team_name": "Hamburger SV", "counter_team_id": "41", "transfer_fee": "loan transfer", "transfer_id": "2382607"}]}, {"team": {"team_name": "Eintracht Frankfurt", "team_id": "24", "team_country": "Germany"}, "in": [{"player_name": "Tuta", "player_id": "546213", "player_age": "19", "player_nat": ["Brazil"], "player_pos": "CB", "market_val": "€6.00m", "counter_team_country": "Brazil", "counter_team_name": "FC São Paulo B", "counter_team_id": "14708", "transfer_fee": "€1.80m", "transfer_id": "2388745"}, {"player_name": "Martin Hinteregger", "player_id": "85789", "player_age": "26", "player_nat": ["Austria"], "player_pos": "CB", "market_val": "€13.00m", "counter_team_country": "Germany", "counter_team_name": "FC Augsburg", "counter_team_id": "167", "transfer_fee": "Loan fee:€800Th.", "transfer_id": "2388759"}, {"player_name": "Almamy Touré", "player_id": "216181", "player_age": "22", "player_nat": ["France", "Mali"], "player_pos": "RB", "market_val": "€5.50m", "counter_team_country": "France", "counter_team_name": "AS Monaco", "counter_team_id": "162", "transfer_fee": "€750Th.", "transfer_id": "2389051"}, {"player_name": "Sebastian Rode", "player_id": "44466", "player_age": "28", "player_nat": ["Germany"], "player_pos": "CM", "market_val": "€4.00m", "counter_team_country": "Germany", "counter_team_name": "Borussia Dortmund", "counter_team_id": "16", "transfer_fee": "loan transfer", "transfer_id": "2348897"}, {"player_name": "Nils Stendera", "player_id": "336329", "player_age": "18", "player_nat": ["Germany"], "player_pos": "CM", "market_val": "€100Th.", "counter_team_country": "Germany", "counter_team_name": "Eintracht Frankfurt U19", "counter_team_id": "5372", "transfer_fee": "-", "transfer_id": "2371486"}, {"player_name": "Patrick Finger", "player_id": "406604", "player_age": "18", "player_nat": ["Germany"], "player_pos": "AM", "market_val": "-", "counter_team_country": "Germany", "counter_team_name": "Eintracht Frankfurt U19", "counter_team_id": "5372", "transfer_fee": "-", "transfer_id": "2391324"}], "left": [{"player_name": "Carlos Salcedo", "player_id": "256866", "player_age": "25", "player_nat": ["Mexico"], "player_pos": "CB", "market_val": "€5.00m", "counter_team_country": "Mexico", "counter_team_name": "Tigres UANL", "counter_team_id": "7055", "transfer_fee": "€8.80m", "transfer_id": "2377081"}, {"player_name": "Nicolai Müller", "player_id": "39426", "player_age": "31", "player_nat": ["Germany"], "player_pos": "AM", "market_val": "€500Th.", "counter_team_country": "Germany", "counter_team_name": "Hannover 96", "counter_team_id": "42", "transfer_fee": "Loan fee:€200Th.", "transfer_id": "2351352"}, {"player_name": "Marco Fabián", "player_id": "67685", "player_age": "29", "player_nat": ["Mexico"], "player_pos": "AM", "market_val": "€800Th.", "counter_team_country": "United States", "counter_team_name": "Philadelphia Union", "counter_team_id": "25467", "transfer_fee": "free transfer", "transfer_id": "2399282"}, {"player_name": "Noel Knothe", "player_id": "379960", "player_age": "19", "player_nat": ["Germany"], "player_pos": "CB", "market_val": "€250Th.", "counter_team_country": "Germany", "counter_team_name": "FC Pipinsried", "counter_team_id": "4191", "transfer_fee": "loan transfer", "transfer_id": "2385458"}, {"player_name": "Deji Beyreuther", "player_id": "482163", "player_age": "19", "player_nat": ["Germany", "Nigeria"], "player_pos": "LB", "market_val": "€100Th.", "counter_team_country": "Germany", "counter_team_name": "Chemnitzer FC", "counter_team_id": "21", "transfer_fee": "loan transfer", "transfer_id": "2346050"}, {"player_name": "Felix Wiedwald", "player_id": "44594", "player_age": "28", "player_nat": ["Germany"], "player_pos": "GK", "market_val": "€300Th.", "counter_team_country": "Germany", "counter_team_name": "MSV Duisburg", "counter_team_id": "52", "transfer_fee": "loan transfer", "transfer_id": "2355097"}, {"player_name": "Allan", "player_id": "385271", "player_age": "21", "player_nat": ["Brazil"], "player_pos": "DM", "market_val": "€3.50m", "counter_team_country": "England", "counter_team_name": "Liverpool FC U23", "counter_team_id": "9252", "transfer_fee": "End of loanJan 31, 2019", "transfer_id": "2194925"}, {"player_name": "Chico Geraldes", "player_id": "257456", "player_age": "23", "player_nat": ["Portugal"], "player_pos": "AM", "market_val": "€900Th.", "counter_team_country": "Portugal", "counter_team_name": "Sporting CP", "counter_team_id": "336", "transfer_fee": "End of loanDec 23, 2018", "transfer_id": "2197098"}]}, {"team": {"team_name": "Borussia Mönchengladbach", "team_id": "18", "team_country": "Germany"}, "in": null, "left": [{"player_name": "Lászlo Bénes", "player_id": "243188", "player_age": "21", "player_nat": ["Slovakia"], "player_pos": "CM", "market_val": "€4.00m", "counter_team_country": "Germany", "counter_team_name": "Holstein Kiel", "counter_team_id": "269", "transfer_fee": "loan transfer", "transfer_id": "2385229"}]}, {"team": {"team_name": "Hertha BSC", "team_id": "44", "team_country": "Germany"}, "in": [{"player_name": "Maximilian Pronichev", "player_id": "243805", "player_age": "21", "player_nat": ["Russia"], "player_pos": "SS", "market_val": "€150Th.", "counter_team_country": "Germany", "counter_team_name": "FC Erzgebirge Aue", "counter_team_id": "94", "transfer_fee": "End of loanDec 31, 2018", "transfer_id": "2201331"}], "left": [{"player_name": "Alexander Esswein", "player_id": "45662", "player_age": "28", "player_nat": ["Germany"], "player_pos": "RW", "market_val": "€500Th.", "counter_team_country": "Germany", "counter_team_name": "VfB Stuttgart", "counter_team_id": "79", "transfer_fee": "Loan fee:€400Th.", "transfer_id": "2345706"}, {"player_name": "Sinan Kurt", "player_id": "170530", "player_age": "22", "player_nat": ["Germany", "Turkey"], "player_pos": "LW", "market_val": "€100Th.", "counter_team_country": "Austria", "counter_team_name": "WSG Wattens", "counter_team_id": "2446", "transfer_fee": "free transfer", "transfer_id": "2391032"}, {"player_name": "Maximilian Pronichev", "player_id": "243805", "player_age": "21", "player_nat": ["Russia"], "player_pos": "SS", "market_val": "€150Th.", "counter_team_country": "Germany", "counter_team_name": "Hallescher FC", "counter_team_id": "440", "transfer_fee": "loan transfer", "transfer_id": "2358063"}, {"player_name": "Sidney Friede", "player_id": "282658", "player_age": "20", "player_nat": ["Germany", "Nigeria"], "player_pos": "CM", "market_val": "-", "counter_team_country": "Belgium", "counter_team_name": "Royal Excel Mouscron", "counter_team_id": "29228", "transfer_fee": "loan transfer", "transfer_id": "2372612"}, {"player_name": "Muhammed Kiprit", "player_id": "362746", "player_age": "19", "player_nat": ["Turkey", "Germany"], "player_pos": "CF", "market_val": "€350Th.", "counter_team_country": "Austria", "counter_team_name": "FC Wacker Innsbruck", "counter_team_id": "2444", "transfer_fee": "loan transfer", "transfer_id": "2396494"}]}, {"team": {"team_name": "SV Werder Bremen", "team_id": "86", "team_country": "Germany"}, "in": [{"player_name": "Romano Schmid", "player_id": "346853", "player_age": "18", "player_nat": ["Austria"], "player_pos": "AM", "market_val": "€4.00m", "counter_team_country": "Austria", "counter_team_name": "Red Bull Salzburg", "counter_team_id": "409", "transfer_fee": "€1.00m", "transfer_id": "2356025"}, {"player_name": "Josh Sargent", "player_id": "393325", "player_age": "18", "player_nat": ["United States"], "player_pos": "CF", "market_val": "€8.00m", "counter_team_country": "Germany", "counter_team_name": "SV Werder Bremen II", "counter_team_id": "87", "transfer_fee": "-", "transfer_id": "2040321"}], "left": [{"player_name": "Florian Kainz", "player_id": "106270", "player_age": "26", "player_nat": ["Austria"], "player_pos": "LW", "market_val": "€3.50m", "counter_team_country": "Germany", "counter_team_name": "1. FC Köln", "counter_team_id": "3", "transfer_fee": "€3.00m", "transfer_id": "2373975"}, {"player_name": "Jaroslav Drobny", "player_id": "12864", "player_age": "39", "player_nat": ["Czech Republic"], "player_pos": "GK", "market_val": "-", "counter_team_country": "Germany", "counter_team_name": "Fortuna Düsseldorf", "counter_team_id": "38", "transfer_fee": "free transfer", "transfer_id": "2367648"}, {"player_name": "Luca Caldirola", "player_id": "88680", "player_age": "27", "player_nat": ["Italy"], "player_pos": "CB", "market_val": "€1.80m", "counter_team_country": "Italy", "counter_team_name": "Benevento Calcio", "counter_team_id": "4171", "transfer_fee": "free transfer", "transfer_id": "2387638"}, {"player_name": "Ole Käuper", "player_id": "195676", "player_age": "21", "player_nat": ["Germany"], "player_pos": "DM", "market_val": "€250Th.", "counter_team_country": "Germany", "counter_team_name": "FC Erzgebirge Aue", "counter_team_id": "94", "transfer_fee": "loan transfer", "transfer_id": "2358879"}, {"player_name": "Romano Schmid", "player_id": "346853", "player_age": "19", "player_nat": ["Austria"], "player_pos": "AM", "market_val": "€4.00m", "counter_team_country": "Austria", "counter_team_name": "Wolfsberger AC", "counter_team_id": "4441", "transfer_fee": "loan transfer", "transfer_id": "2395571"}, {"player_name": "Michael Zetterer", "player_id": "196813", "player_age": "23", "player_nat": ["Germany"], "player_pos": "GK", "market_val": "€800Th.", "counter_team_country": "Austria", "counter_team_name": "SK Austria Klagenfurt", "counter_team_id": "28760", "transfer_fee": "loan transfer", "transfer_id": "2396286"}]}, {"team": {"team_name": "FC Augsburg", "team_id": "167", "team_country": "Germany"}, "in": [{"player_name": "Reece Oxford", "player_id": "314295", "player_age": "20", "player_nat": ["England", "Jamaica"], "player_pos": "CB", "market_val": "€5.00m", "counter_team_country": "England", "counter_team_name": "West Ham United", "counter_team_id": "379", "transfer_fee": "Loan fee:€500Th.", "transfer_id": "2389221"}, {"player_name": "Gregor Kobel", "player_id": "257814", "player_age": "21", "player_nat": ["Switzerland"], "player_pos": "GK", "market_val": "€18.00m", "counter_team_country": "Germany", "counter_team_name": "TSG 1899 Hoffenheim", "counter_team_id": "533", "transfer_fee": "Loan fee:€150Th.", "transfer_id": "2356242"}], "left": [{"player_name": "Martin Hinteregger", "player_id": "85789", "player_age": "26", "player_nat": ["Austria"], "player_pos": "CB", "market_val": "€13.00m", "counter_team_country": "Germany", "counter_team_name": "Eintracht Frankfurt", "counter_team_id": "24", "transfer_fee": "Loan fee:€800Th.", "transfer_id": "2388759"}, {"player_name": "Caiuby", "player_id": "54137", "player_age": "30", "player_nat": ["Brazil"], "player_pos": "SS", "market_val": "€200Th.", "counter_team_country": "Switzerland", "counter_team_name": "Grasshopper Club Zurich", "counter_team_id": "504", "transfer_fee": "loan transfer", "transfer_id": "2404408"}]}, {"team": {"team_name": "Hannover 96", "team_id": "42", "team_country": "Germany"}, "in": [{"player_name": "Kevin Akpoguma", "player_id": "160241", "player_age": "23", "player_nat": ["Nigeria", "Germany"], "player_pos": "CB", "market_val": "€5.00m", "counter_team_country": "Germany", "counter_team_name": "TSG 1899 Hoffenheim", "counter_team_id": "533", "transfer_fee": "Loan fee:€220Th.", "transfer_id": "2350974"}, {"player_name": "Nicolai Müller", "player_id": "39426", "player_age": "31", "player_nat": ["Germany"], "player_pos": "AM", "market_val": "€500Th.", "counter_team_country": "Germany", "counter_team_name": "Eintracht Frankfurt", "counter_team_id": "24", "transfer_fee": "Loan fee:€200Th.", "transfer_id": "2351352"}, {"player_name": "Samuel Sahin-Radlinger", "player_id": "77563", "player_age": "26", "player_nat": ["Austria"], "player_pos": "GK", "market_val": "€350Th.", "counter_team_country": "Norway", "counter_team_name": "SK Brann", "counter_team_id": "1100", "transfer_fee": "End of loanDec 31, 2018", "transfer_id": "2020343"}, {"player_name": "Uffe Bech", "player_id": "94939", "player_age": "25", "player_nat": ["Denmark"], "player_pos": "RW", "market_val": "€150Th.", "counter_team_country": "Denmark", "counter_team_name": "Bröndby IF", "counter_team_id": "206", "transfer_fee": "End of loanDec 31, 2018", "transfer_id": "2246825"}, {"player_name": "Jonathas", "player_id": "58345", "player_age": "29", "player_nat": ["Brazil"], "player_pos": "CF", "market_val": "€900Th.", "counter_team_country": "Brazil", "counter_team_name": "Sport Club Corinthians Paulista", "counter_team_id": "199", "transfer_fee": "End of loanJan 18, 2019", "transfer_id": "2373572"}], "left": [{"player_name": "Philipp Tschauner", "player_id": "21726", "player_age": "33", "player_nat": ["Germany"], "player_pos": "GK", "market_val": "€300Th.", "counter_team_country": "Germany", "counter_team_name": "FC Ingolstadt 04", "counter_team_id": "4795", "transfer_fee": "Loan fee:€90Th.", "transfer_id": "2351019"}]}, {"team": {"team_name": "SC Freiburg", "team_id": "60", "team_country": "Germany"}, "in": [{"player_name": "Vincenzo Grifo", "player_id": "185077", "player_age": "25", "player_nat": ["Italy", "Germany"], "player_pos": "LW", "market_val": "€12.00m", "counter_team_country": "Germany", "counter_team_name": "TSG 1899 Hoffenheim", "counter_team_id": "533", "transfer_fee": "Loan fee:€600Th.", "transfer_id": "2358749"}], "left": [{"player_name": "Caleb Stanko", "player_id": "190269", "player_age": "25", "player_nat": ["United States", "Poland"], "player_pos": "DM", "market_val": "€400Th.", "counter_team_country": "United States", "counter_team_name": "FC Cincinnati", "counter_team_id": "51772", "transfer_fee": "€200Th.", "transfer_id": "2379795"}, {"player_name": "Patrick Kammerbauer", "player_id": "227087", "player_age": "21", "player_nat": ["Germany"], "player_pos": "DM", "market_val": "€325Th.", "counter_team_country": "Germany", "counter_team_name": "Holstein Kiel", "counter_team_id": "269", "transfer_fee": "loan transfer", "transfer_id": "2385137"}, {"player_name": "Yoric Ravet", "player_id": "82461", "player_age": "29", "player_nat": ["France"], "player_pos": "RW", "market_val": "€900Th.", "counter_team_country": "Switzerland", "counter_team_name": "Grasshopper Club Zurich", "counter_team_id": "504", "transfer_fee": "loan transfer", "transfer_id": "2397355"}]}, {"team": {"team_name": "VfL Wolfsburg", "team_id": "82", "team_country": "Germany"}, "in": [{"player_name": "Riechedly Bazoer", "player_id": "216443", "player_age": "22", "player_nat": ["Netherlands", "Curacao"], "player_pos": "CB", "market_val": "€4.50m", "counter_team_country": "Portugal", "counter_team_name": "FC Porto", "counter_team_id": "720", "transfer_fee": "End of loanJan 6, 2019", "transfer_id": "2247591"}], "left": [{"player_name": "Paul Seguin", "player_id": "183780", "player_age": "23", "player_nat": ["Germany"], "player_pos": "CM", "market_val": "€2.50m", "counter_team_country": "Germany", "counter_team_name": "SpVgg Greuther Fürth", "counter_team_id": "65", "transfer_fee": "Loan fee:€100Th.", "transfer_id": "2372608"}, {"player_name": "Jakub Blaszczykowski", "player_id": "29835", "player_age": "33", "player_nat": ["Poland"], "player_pos": "RW", "market_val": "€150Th.", "counter_team_country": "Poland", "counter_team_name": "Wisla Kraków", "counter_team_id": "422", "transfer_fee": "free transfer", "transfer_id": "2356579"}, {"player_name": "Jeffrey Bruma", "player_id": "88721", "player_age": "27", "player_nat": ["Netherlands", "Suriname"], "player_pos": "CB", "market_val": "€1.00m", "counter_team_country": "Germany", "counter_team_name": "FC Schalke 04", "counter_team_id": "33", "transfer_fee": "loan transfer", "transfer_id": "2388764"}, {"player_name": "Riechedly Bazoer", "player_id": "216443", "player_age": "22", "player_nat": ["Netherlands", "Curacao"], "player_pos": "CB", "market_val": "€4.50m", "counter_team_country": "Netherlands", "counter_team_name": "FC Utrecht", "counter_team_id": "200", "transfer_fee": "loan transfer", "transfer_id": "2360450"}]}, {"team": {"team_name": "Fortuna Düsseldorf", "team_id": "38", "team_country": "Germany"}, "in": [{"player_name": "Dawid Kownacki", "player_id": "208167", "player_age": "21", "player_nat": ["Poland"], "player_pos": "CF", "market_val": "€1.50m", "counter_team_country": "Italy", "counter_team_name": "UC Sampdoria", "counter_team_id": "1038", "transfer_fee": "Loan fee:€1.25m", "transfer_id": "2389043"}, {"player_name": "Jaroslav Drobny", "player_id": "12864", "player_age": "39", "player_nat": ["Czech Republic"], "player_pos": "GK", "market_val": "-", "counter_team_country": "Germany", "counter_team_name": "SV Werder Bremen", "counter_team_id": "86", "transfer_fee": "free transfer", "transfer_id": "2367648"}, {"player_name": "Markus Suttner", "player_id": "31514", "player_age": "31", "player_nat": ["Austria"], "player_pos": "LB", "market_val": "€600Th.", "counter_team_country": "England", "counter_team_name": "Brighton & Hove Albion", "counter_team_id": "1237", "transfer_fee": "loan transfer", "transfer_id": "2372825"}, {"player_name": "Johannes Bühler", "player_id": "263118", "player_age": "21", "player_nat": ["Germany"], "player_pos": "DM", "market_val": "€100Th.", "counter_team_country": "Without Club", "counter_team_name": "Without Club", "counter_team_id": "515", "transfer_fee": "-", "transfer_id": "2362506"}], "left": [{"player_name": "Taylan Duman", "player_id": "314214", "player_age": "21", "player_nat": ["Germany", "Turkey"], "player_pos": "CM", "market_val": "€300Th.", "counter_team_country": "Germany", "counter_team_name": "Borussia Dortmund II", "counter_team_id": "17", "transfer_fee": "?", "transfer_id": "2381770"}, {"player_name": "Havard Nielsen", "player_id": "136181", "player_age": "25", "player_nat": ["Norway"], "player_pos": "CF", "market_val": "€1.20m", "counter_team_country": "Germany", "counter_team_name": "MSV Duisburg", "counter_team_id": "52", "transfer_fee": "loan transfer", "transfer_id": "2360752"}, {"player_name": "Johannes Bühler", "player_id": "263118", "player_age": "21", "player_nat": ["Germany"], "player_pos": "DM", "market_val": "€100Th.", "counter_team_country": "Germany", "counter_team_name": "VfR Aalen", "counter_team_id": "83", "transfer_fee": "loan transfer", "transfer_id": "2362504"}, {"player_name": "Gökhan Gül", "player_id": "269171", "player_age": "20", "player_nat": ["Germany", "Turkey"], "player_pos": "DM", "market_val": "€250Th.", "counter_team_country": "Germany", "counter_team_name": "SV Wehen Wiesbaden", "counter_team_id": "108", "transfer_fee": "loan transfer", "transfer_id": "2378441"}]}, {"team": {"team_name": "1.FC Nuremberg", "team_id": "4", "team_country": "Germany"}, "in": [{"player_name": "Ivo Ilicevic", "player_id": "30308", "player_age": "32", "player_nat": ["Croatia"], "player_pos": "LW", "market_val": "-", "counter_team_country": "Kazakhstan", "counter_team_name": "Kairat Almaty", "counter_team_id": "10482", "transfer_fee": "free transfer", "transfer_id": "2387363"}, {"player_name": "Simon Rhein", "player_id": "284188", "player_age": "20", "player_nat": ["Germany"], "player_pos": "DM", "market_val": "€500Th.", "counter_team_country": "Germany", "counter_team_name": "1.FC Nuremberg II", "counter_team_id": "473", "transfer_fee": "-", "transfer_id": "2325424"}], "left": null}]